{"cameraMode":{"drawMode":0,"name":"Shaded","section":"Shading Mode"},"sceneLighting":true,"audioPlay":false,"sceneViewState":{"m_AlwaysRefresh":false,"showFog":true,"showSkybox":true,"showFlares":true,"showImageEffects":true,"showParticleSystems":true,"showVisualEffectGraphs":true,"m_FxEnabled":true},"in2DMode":false,"pivot":{"x":6.913366317749023,"y":9.951874732971192,"z":7.338634490966797},"rotation":{"x":0.1360330432653427,"y":-0.7417947053909302,"z":0.15836018323898316,"w":0.6373299956321716},"size":11.075173377990723,"orthographic":false}